log_config_watcher/__init__.py
log_config_watcher/log_config_watcher.py
log_config_watcher-0.3.1.dist-info/LICENSE
log_config_watcher-0.3.1.dist-info/METADATA
log_config_watcher-0.3.1.dist-info/WHEEL
log_config_watcher-0.3.1.dist-info/RECORD
