Metadata-Version: 2.3
Name: log_config_watcher
Version: 0.3.1
Summary: Watches your logging configuration file for change and applies them without requiring an application restart
License: BSD-3-Clause
Author: Robert DeRose
Author-email: rderose@checkpt.com
Requires-Python: >=3.5,<4.0
Classifier: License :: OSI Approved :: BSD License
Classifier: Programming Language :: Python :: 3
Classifier: Programming Language :: Python :: 3.5
Classifier: Programming Language :: Python :: 3.6
Classifier: Programming Language :: Python :: 3.7
Classifier: Programming Language :: Python :: 3.8
Classifier: Programming Language :: Python :: 3.9
Classifier: Programming Language :: Python :: 3.10
Classifier: Programming Language :: Python :: 3.11
Classifier: Programming Language :: Python :: 3.12
Classifier: Programming Language :: Python :: 3.13
Project-URL: Documentation, https://github.com/RobertDeRose/log_config_watcher/blob/main/README.md
Project-URL: Homepage, https://github.com/RobertDeRose/log_config_watcher
